[
    {
        "number": "1'",
        "transcription": [
            {
                "index": 1,
                "signs": [
                    [
                        {
                            "sign": "nu",
                            "type": "Hittite"
                        }
                    ],
                    [
                        {
                            "sign": "d",
                            "type": "Determination"
                        },
                        {
                            "sign": "10",
                            "type": "Numeral"
                        }
                    ],
                    [
                        {
                            "sign": "ka",
                            "type": "Hittite"
                        },
                        {
                            "sign": "la",
                            "type": "Hittite"
                        },
                        {
                            "sign": "an",
                            "type": "Hittite"
                        },
                        {
                            "sign": "<kán",
                            "type": "Hittite"
                        },
                        {
                            "sign": ">za",
                            "type": "Hittite"
                        }
                    ],
                    [
                        {
                            "sign": "ka",
                            "type": "Hittite"
                        }
                    ]
                ]
            },
            {
                "index": 2,
                "signs": []
            }
        ]
    },
    {
        "number": "2'",
        "transcription": [
            {
                "index": 2,
                "signs": [
                    [
                        {
                            "sign": "tal",
                            "type": "Hittite"
                        },
                        {
                            "sign": "li",
                            "type": "Hittite"
                        },
                        {
                            "sign": "ya",
                            "type": "Hittite"
                        },
                        {
                            "sign": "ad",
                            "type": "Hittite"
                        },
                        {
                            "sign": "du",
                            "type": "Hittite"
                        }
                    ]
                ]
            },
            {
                "index": 3,
                "signs": [
                    [
                        {
                            "sign": "GIŠ",
                            "type": "Determination"
                        },
                        {
                            "sign": "x",
                            "type": "Hittite"
                        }
                    ]
                ]
            }
        ]
    },
    {
        "number": "3'",
        "transcription": [
            {
                "index": 3,
                "signs": [
                    [
                        {
                            "sign": "ḫa",
                            "type": "Hittite"
                        },
                        {
                            "sign": "ap",
                            "type": "Hittite"
                        },
                        {
                            "sign": "pu",
                            "type": "Hittite"
                        },
                        {
                            "sign": "ri",
                            "type": "Hittite"
                        },
                        {
                            "sign": "ya",
                            "type": "Hittite"
                        },
                        {
                            "sign": "aš",
                            "type": "Hittite"
                        }
                    ],
                    [
                        {
                            "sign": "a",
                            "type": "Hittite"
                        },
                        {
                            "sign": "aš",
                            "type": "Hittite"
                        },
                        {
                            "sign": "šu",
                            "type": "Hittite"
                        }
                    ]
                ]
            }
        ]
    },
    {
        "number": "4'",
        "transcription": [
            {
                "index": 4,
                "signs": [
                    [
                        {
                            "sign": "šu",
                            "type": "Hittite"
                        },
                        {
                            "sign": "up",
                            "type": "Hittite"
                        },
                        {
                            "sign": "pí",
                            "type": "Hittite"
                        },
                        {
                            "sign": "iš",
                            "type": "Hittite"
                        },
                        {
                            "sign": "ša",
                            "type": "Hittite"
                        },
                        {
                            "sign": "at",
                            "type": "Hittite"
                        },
                        {
                            "sign": "ta",
                            "type": "Hittite"
                        }
                    ]
                ]
            }
        ]
    },
    {
        "number": "5'",
        "transcription": [
            {
                "index": 4,
                "signs": [
                    [
                        {
                            "sign": "šu",
                            "type": "Hittite"
                        },
                        {
                            "sign": "up",
                            "type": "Hittite"
                        },
                        {
                            "sign": "pí",
                            "type": "Hittite"
                        },
                        {
                            "sign": "iš",
                            "type": "Hittite"
                        },
                        {
                            "sign": "ke",
                            "type": "Hittite"
                        },
                        {
                            "sign": "ed",
                            "type": "Hittite"
                        },
                        {
                            "sign": "du",
                            "type": "Hittite"
                        }
                    ]
                ]
            },
            {
                "index": 5,
                "signs": []
            }
        ]
    },
    {
        "number": "6'",
        "transcription": [
            {
                "index": 6,
                "signs": [
                    [
                        {
                            "sign": "na",
                            "type": "Hittite"
                        },
                        {
                            "sign": "aš",
                            "type": "Hittite"
                        }
                    ],
                    [
                        {
                            "sign": "ar",
                            "type": "Hittite"
                        },
                        {
                            "sign": "li",
                            "type": "Hittite"
                        },
                        {
                            "sign": "pa",
                            "type": "Hittite"
                        }
                    ]
                ]
            }
        ]
    },
    {
        "number": "7'",
        "transcription": [
            {
                "index": 7,
                "signs": [
                    [
                        {
                            "sign": "_",
                            "type": "Hittite"
                        }
                    ],
                    [
                        {
                            "sign": "x",
                            "type": "Hittite"
                        }
                    ]
                ]
            }
        ]
    }
]