[
    {
        "number": "Vs. II 1'",
        "transcription": [
            {
                "index": 1,
                "signs": [
                    [
                        {
                            "reading": "pa",
                            "type": "Hittite"
                        },
                        {
                            "reading": "ap",
                            "type": "Hittite"
                        },
                        {
                            "reading": "ra",
                            "type": "Hittite"
                        },
                        {
                            "reading": "tar",
                            "type": "Hittite"
                        }
                    ],
                    [
                        {
                            "reading": "mu",
                            "type": "Hittite"
                        },
                        {
                            "reading": "la",
                            "type": "Hittite"
                        },
                        {
                            "reading": "a",
                            "type": "Hittite"
                        },
                        {
                            "reading": "tar",
                            "type": "Hittite"
                        }
                    ]
                ]
            }
        ]
    },
    {
        "number": "Vs. II 2'",
        "transcription": [
            {
                "index": 1,
                "signs": [
                    [
                        {
                            "reading": "SUD",
                            "type": "Sumerogram"
                        },
                        {
                            "reading": "ru",
                            "type": "Hittite"
                        }
                    ]
                ]
            },
            {
                "index": 2,
                "signs": [
                    [
                        {
                            "reading": "IGI",
                            "type": "Sumerogram"
                        },
                        {
                            "reading": "ḪI",
                            "type": "Determination"
                        },
                        {
                            "reading": "A",
                            "type": "Determination"
                        },
                        {
                            "reading": "wa",
                            "type": "Hittite"
                        },
                        {
                            "reading": "za",
                            "type": "Hittite"
                        }
                    ],
                    [
                        {
                            "reading": "SUD",
                            "type": "Sumerogram"
                        },
                        {
                            "reading": "ru",
                            "type": "Hittite"
                        }
                    ]
                ]
            },
            {
                "index": 3,
                "signs": [
                    [
                        {
                            "reading": "ŠU",
                            "type": "Sumerogram"
                        },
                        {
                            "reading": "MEŠ",
                            "type": "Determination"
                        },
                        {
                            "reading": "za",
                            "type": "Hittite"
                        }
                    ]
                ]
            }
        ]
    },
    {
        "number": "Vs. II 3'",
        "transcription": [
            {
                "index": 3,
                "signs": [
                    [
                        {
                            "reading": "SUD",
                            "type": "Sumerogram"
                        },
                        {
                            "reading": "ru",
                            "type": "Hittite"
                        }
                    ]
                ]
            },
            {
                "index": 4,
                "signs": [
                    [
                        {
                            "reading": "9",
                            "type": "Numeral"
                        },
                        {
                            "reading": "za",
                            "type": "Hittite"
                        }
                    ],
                    [
                        {
                            "reading": "UZU",
                            "type": "Determination"
                        },
                        {
                            "reading": "ÚR",
                            "type": "Sumerogram"
                        },
                        {
                            "reading": "za",
                            "type": "Hittite"
                        }
                    ],
                    [
                        {
                            "reading": "SUD",
                            "type": "Sumerogram"
                        },
                        {
                            "reading": "ru",
                            "type": "Hittite"
                        }
                    ]
                ]
            }
        ]
    },
    {
        "number": "Vs. II 4'",
        "transcription": [
            {
                "index": 5,
                "signs": [
                    [
                        {
                            "reading": "na",
                            "type": "Hittite"
                        },
                        {
                            "reading": "at",
                            "type": "Hittite"
                        }
                    ],
                    [
                        {
                            "reading": "ḪUL",
                            "type": "Sumerogram"
                        },
                        {
                            "reading": "u",
                            "type": "Hittite"
                        },
                        {
                            "reading": "wa",
                            "type": "Hittite"
                        },
                        {
                            "reading": "aš",
                            "type": "Hittite"
                        }
                    ],
                    [
                        {
                            "reading": "UN",
                            "type": "Sumerogram"
                        },
                        {
                            "reading": "MEŠ",
                            "type": "Determination"
                        },
                        {
                            "reading": "aš",
                            "type": "Hittite"
                        }
                    ],
                    [
                        {
                            "reading": "ḫar",
                            "type": "Hittite"
                        },
                        {
                            "reading": "pa",
                            "type": "Hittite"
                        },
                        {
                            "reading": "na",
                            "type": "Hittite"
                        },
                        {
                            "reading": "al",
                            "type": "Hittite"
                        },
                        {
                            "reading": "li",
                            "type": "Hittite"
                        },
                        {
                            "reading": "ia",
                            "type": "Hittite"
                        },
                        {
                            "reading": "aš",
                            "type": "Hittite"
                        }
                    ],
                    [
                        {
                            "reading": "pé",
                            "type": "Hittite"
                        },
                        {
                            "reading": "eš",
                            "type": "Hittite"
                        },
                        {
                            "reading": "ki",
                            "type": "Hittite"
                        }
                    ]
                ]
            }
        ]
    },
    {
        "number": "Vs. II 5'",
        "transcription": [
            {
                "index": 6,
                "signs": [
                    [
                        {
                            "reading": "EGIR",
                            "type": "Sumerogram"
                        },
                        {
                            "reading": "ŠÚ",
                            "type": "Akkadogram"
                        },
                        {
                            "reading": "kán",
                            "type": "Hittite"
                        }
                    ],
                    [
                        {
                            "reading": "GADA",
                            "type": "Sumerogram"
                        }
                    ],
                    [
                        {
                            "reading": "an",
                            "type": "Hittite"
                        },
                        {
                            "reading": "da",
                            "type": "Hittite"
                        }
                    ],
                    [
                        {
                            "reading": "QA",
                            "type": "Akkadogram"
                        },
                        {
                            "reading": "TAM",
                            "type": "Akkadogram"
                        },
                        {
                            "reading": "MA",
                            "type": "Akkadogram"
                        }
                    ],
                    [
                        {
                            "reading": "ḫa",
                            "type": "Hittite"
                        },
                        {
                            "reading": "ma",
                            "type": "Hittite"
                        },
                        {
                            "reading": "ak",
                            "type": "Hittite"
                        },
                        {
                            "reading": "zi",
                            "type": "Hittite"
                        }
                    ]
                ]
            }
        ]
    },
    {
        "number": "Vs. II 6'",
        "transcription": [
            {
                "index": 7,
                "signs": [
                    [
                        {
                            "reading": "nu",
                            "type": "Hittite"
                        }
                    ],
                    [
                        {
                            "reading": "te",
                            "type": "Hittite"
                        },
                        {
                            "reading": "ez",
                            "type": "Hittite"
                        },
                        {
                            "reading": "zi",
                            "type": "Hittite"
                        }
                    ]
                ]
            },
            {
                "index": 8,
                "signs": [
                    [
                        {
                            "reading": "GADA",
                            "type": "Sumerogram"
                        }
                    ],
                    [
                        {
                            "reading": "GIM",
                            "type": "Sumerogram"
                        },
                        {
                            "reading": "an",
                            "type": "Hittite"
                        }
                    ],
                    [
                        {
                            "reading": "LÚ",
                            "type": "Determination"
                        },
                        {
                            "reading": "MEŠ",
                            "type": "Determination"
                        },
                        {
                            "reading": "ŠÀ",
                            "type": "Sumerogram"
                        },
                        {
                            "reading": "TAM",
                            "type": "Sumerogram"
                        }
                    ]
                ]
            }
        ]
    },
    {
        "number": "Vs. II 7'",
        "transcription": [
            {
                "index": 8,
                "signs": [
                    [
                        {
                            "reading": "ta",
                            "type": "Hittite"
                        },
                        {
                            "reading": "an",
                            "type": "Hittite"
                        },
                        {
                            "reading": "na",
                            "type": "Hittite"
                        },
                        {
                            "reading": "ra",
                            "type": "Hittite"
                        },
                        {
                            "reading": "an",
                            "type": "Hittite"
                        },
                        {
                            "reading": "tan@x",
                            "type": "Hittite"
                        }
                    ],
                    [
                        {
                            "reading": "KIN",
                            "type": "Sumerogram"
                        },
                        {
                            "reading": "zi",
                            "type": "Hittite"
                        }
                    ]
                ]
            },
            {
                "index": 9,
                "signs": [
                    [
                        {
                            "reading": "nu",
                            "type": "Hittite"
                        },
                        {
                            "reading": "uš",
                            "type": "Hittite"
                        },
                        {
                            "reading": "ši",
                            "type": "Hittite"
                        },
                        {
                            "reading": "kán",
                            "type": "Hittite"
                        }
                    ]
                ]
            }
        ]
    },
    {
        "number": "Vs. II 8'",
        "transcription": [
            {
                "index": 9,
                "signs": [
                    [
                        {
                            "reading": "ma",
                            "type": "Hittite"
                        },
                        {
                            "reading": "ri",
                            "type": "Hittite"
                        },
                        {
                            "reading": "iḫ",
                            "type": "Hittite"
                        },
                        {
                            "reading": "ši",
                            "type": "Hittite"
                        },
                        {
                            "reading": "in",
                            "type": "Hittite"
                        }
                    ],
                    [
                        {
                            "reading": "ar",
                            "type": "Hittite"
                        },
                        {
                            "reading": "ḫa",
                            "type": "Hittite"
                        }
                    ],
                    [
                        {
                            "reading": "pár",
                            "type": "Hittite"
                        },
                        {
                            "reading": "ku",
                            "type": "Hittite"
                        },
                        {
                            "reading": "nu",
                            "type": "Hittite"
                        },
                        {
                            "reading": "uz",
                            "type": "Hittite"
                        },
                        {
                            "reading": "zi",
                            "type": "Hittite"
                        }
                    ]
                ]
            }
        ]
    },
    {
        "number": "Vs. II 9'",
        "transcription": [
            {
                "index": 10,
                "signs": [
                    [
                        {
                            "reading": "na",
                            "type": "Hittite"
                        },
                        {
                            "reading": "at",
                            "type": "Hittite"
                        }
                    ],
                    [
                        {
                            "reading": "ḫar",
                            "type": "Hittite"
                        },
                        {
                            "reading": "ke",
                            "type": "Hittite"
                        },
                        {
                            "reading": "e",
                            "type": "Hittite"
                        },
                        {
                            "reading": "eš",
                            "type": "Hittite"
                        },
                        {
                            "reading": "zi",
                            "type": "Hittite"
                        }
                    ]
                ]
            }
        ]
    },
    {
        "number": "Vs. II 10'",
        "transcription": [
            {
                "index": 11,
                "signs": [
                    [
                        {
                            "reading": "ḪUL",
                            "type": "Sumerogram"
                        },
                        {
                            "reading": "u",
                            "type": "Hittite"
                        },
                        {
                            "reading": "wa",
                            "type": "Hittite"
                        },
                        {
                            "reading": "aš",
                            "type": "Hittite"
                        },
                        {
                            "reading": "ša",
                            "type": "Hittite"
                        }
                    ],
                    [
                        {
                            "reading": "UN",
                            "type": "Sumerogram"
                        },
                        {
                            "reading": "MEŠ",
                            "type": "Determination"
                        },
                        {
                            "reading": "aš",
                            "type": "Hittite"
                        }
                    ],
                    [
                        {
                            "reading": "AN",
                            "type": "Akkadogram"
                        },
                        {
                            "reading": "ZE",
                            "type": "Akkadogram"
                        },
                        {
                            "reading": "EL",
                            "type": "Akkadogram"
                        },
                        {
                            "reading": "LU",
                            "type": "Akkadogram"
                        }
                    ]
                ]
            }
        ]
    },
    {
        "number": "Vs. II 11'",
        "transcription": [
            {
                "index": 11,
                "signs": [
                    [
                        {
                            "reading": "ḫur",
                            "type": "Hittite"
                        },
                        {
                            "reading": "ki",
                            "type": "Hittite"
                        },
                        {
                            "reading": "la",
                            "type": "Hittite"
                        },
                        {
                            "reading": "za",
                            "type": "Hittite"
                        }
                    ],
                    [
                        {
                            "reading": "pa",
                            "type": "Hittite"
                        },
                        {
                            "reading": "ap",
                            "type": "Hittite"
                        },
                        {
                            "reading": "ra",
                            "type": "Hittite"
                        },
                        {
                            "reading": "an",
                            "type": "Hittite"
                        },
                        {
                            "reading": "na",
                            "type": "Hittite"
                        },
                        {
                            "reading": "za",
                            "type": "Hittite"
                        }
                    ]
                ]
            }
        ]
    },
    {
        "number": "Vs. II 12'",
        "transcription": [
            {
                "index": 11,
                "signs": [
                    [
                        {
                            "reading": "mu",
                            "type": "Hittite"
                        },
                        {
                            "reading": "la",
                            "type": "Hittite"
                        },
                        {
                            "reading": "at",
                            "type": "Hittite"
                        },
                        {
                            "reading": "na",
                            "type": "Hittite"
                        },
                        {
                            "reading": "za",
                            "type": "Hittite"
                        }
                    ]
                ]
            }
        ]
    },
    {
        "number": "Vs. II 13'",
        "transcription": [
            {
                "index": 11,
                "signs": [
                    [
                        {
                            "reading": "NÍ",
                            "type": "Sumerogram"
                        },
                        {
                            "reading": "TE",
                            "type": "Sumerogram"
                        }
                    ],
                    [
                        {
                            "reading": "LUGAL",
                            "type": "Sumerogram"
                        }
                    ],
                    [
                        {
                            "reading": "QA",
                            "type": "Akkadogram"
                        },
                        {
                            "reading": "TAM",
                            "type": "Akkadogram"
                        },
                        {
                            "reading": "MA",
                            "type": "Akkadogram"
                        }
                    ],
                    [
                        {
                            "reading": "pár",
                            "type": "Hittite"
                        },
                        {
                            "reading": "ku",
                            "type": "Hittite"
                        },
                        {
                            "reading": "eš",
                            "type": "Hittite"
                        },
                        {
                            "reading": "du",
                            "type": "Hittite"
                        }
                    ]
                ]
            }
        ]
    },
    {
        "number": "Rs. III 1",
        "transcription": [
            {
                "index": 12,
                "signs": [
                    [
                        {
                            "reading": "EGIR",
                            "type": "Sumerogram"
                        },
                        {
                            "reading": "ŠÚ",
                            "type": "Akkadogram"
                        },
                        {
                            "reading": "ma",
                            "type": "Hittite"
                        },
                        {
                            "reading": "kán",
                            "type": "Hittite"
                        }
                    ],
                    [
                        {
                            "reading": "GIŠ",
                            "type": "Determination"
                        },
                        {
                            "reading": "ḫa",
                            "type": "Hittite"
                        },
                        {
                            "reading": "at",
                            "type": "Hittite"
                        },
                        {
                            "reading": "ta",
                            "type": "Hittite"
                        },
                        {
                            "reading": "lu",
                            "type": "Hittite"
                        }
                    ],
                    [
                        {
                            "reading": "tar",
                            "type": "Hittite"
                        },
                        {
                            "reading": "zu",
                            "type": "Hittite"
                        },
                        {
                            "reading": "wa",
                            "type": "Hittite"
                        },
                        {
                            "reading": "an",
                            "type": "Hittite"
                        }
                    ]
                ]
            }
        ]
    },
    {
        "number": "Rs. III 2",
        "transcription": [
            {
                "index": 12,
                "signs": [
                    [
                        {
                            "reading": "GI",
                            "type": "Determination"
                        },
                        {
                            "reading": "pád",
                            "type": "Hittite"
                        },
                        {
                            "reading": "da",
                            "type": "Hittite"
                        },
                        {
                            "reading": "a",
                            "type": "Hittite"
                        },
                        {
                            "reading": "ni",
                            "type": "Hittite"
                        }
                    ],
                    [
                        {
                            "reading": "da",
                            "type": "Hittite"
                        },
                        {
                            "reading": "a",
                            "type": "Hittite"
                        },
                        {
                            "reading": "i",
                            "type": "Hittite"
                        }
                    ]
                ]
            },
            {
                "index": 13,
                "signs": [
                    [
                        {
                            "reading": "na",
                            "type": "Hittite"
                        },
                        {
                            "reading": "at",
                            "type": "Hittite"
                        }
                    ],
                    [
                        {
                            "reading": "LUGAL",
                            "type": "Sumerogram"
                        },
                        {
                            "reading": "i",
                            "type": "Hittite"
                        }
                    ]
                ]
            }
        ]
    },
    {
        "number": "Rs. III 3",
        "transcription": [
            {
                "index": 13,
                "signs": [
                    [
                        {
                            "reading": "še",
                            "type": "Hittite"
                        },
                        {
                            "reading": "er",
                            "type": "Hittite"
                        }
                    ],
                    [
                        {
                            "reading": "ar",
                            "type": "Hittite"
                        },
                        {
                            "reading": "ḫa",
                            "type": "Hittite"
                        }
                    ],
                    [
                        {
                            "reading": "BAL",
                            "type": "Sumerogram"
                        },
                        {
                            "reading": "zi",
                            "type": "Hittite"
                        }
                    ]
                ]
            },
            {
                "index": 14,
                "signs": [
                    [
                        {
                            "reading": "nu",
                            "type": "Hittite"
                        }
                    ],
                    [
                        {
                            "reading": "te",
                            "type": "Hittite"
                        },
                        {
                            "reading": "ez",
                            "type": "Hittite"
                        },
                        {
                            "reading": "zi",
                            "type": "Hittite"
                        }
                    ]
                ]
            }
        ]
    },
    {
        "number": "Rs. III 4",
        "transcription": [
            {
                "index": 15,
                "signs": [
                    [
                        {
                            "reading": "d",
                            "type": "Determination"
                        },
                        {
                            "reading": "za",
                            "type": "Hittite"
                        },
                        {
                            "reading": "ar",
                            "type": "Hittite"
                        },
                        {
                            "reading": "ni",
                            "type": "Hittite"
                        },
                        {
                            "reading": "za",
                            "type": "Hittite"
                        },
                        {
                            "reading": "aš",
                            "type": "Hittite"
                        }
                    ],
                    [
                        {
                            "reading": "d",
                            "type": "Determination"
                        },
                        {
                            "reading": "tar",
                            "type": "Hittite"
                        },
                        {
                            "reading": "pa",
                            "type": "Hittite"
                        },
                        {
                            "reading": "ad",
                            "type": "Hittite"
                        },
                        {
                            "reading": "da",
                            "type": "Hittite"
                        },
                        {
                            "reading": "aš",
                            "type": "Hittite"
                        },
                        {
                            "reading": "ši",
                            "type": "Hittite"
                        },
                        {
                            "reading": "iš",
                            "type": "Hittite"
                        }
                    ]
                ]
            }
        ]
    },
    {
        "number": "Rs. III 5",
        "transcription": [
            {
                "index": 15,
                "signs": [
                    [
                        {
                            "reading": "d",
                            "type": "Determination"
                        },
                        {
                            "reading": "A",
                            "type": "Hittite"
                        },
                        {
                            "reading": "la",
                            "type": "Hittite"
                        },
                        {
                            "reading": "a",
                            "type": "Hittite"
                        },
                        {
                            "reading": "ú",
                            "type": "Hittite"
                        },
                        {
                            "reading": "wa",
                            "type": "Hittite"
                        },
                        {
                            "reading": "i",
                            "type": "Hittite"
                        },
                        {
                            "reading": "mi",
                            "type": "Hittite"
                        },
                        {
                            "reading": "iš",
                            "type": "Hittite"
                        }
                    ],
                    [
                        {
                            "reading": "d",
                            "type": "Determination"
                        },
                        {
                            "reading": "ma",
                            "type": "Hittite"
                        },
                        {
                            "reading": "am",
                            "type": "Hittite"
                        },
                        {
                            "reading": "ma",
                            "type": "Hittite"
                        },
                        {
                            "reading": "a",
                            "type": "Hittite"
                        },
                        {
                            "reading": "i",
                            "type": "Hittite"
                        },
                        {
                            "reading": "mi",
                            "type": "Hittite"
                        },
                        {
                            "reading": "iš",
                            "type": "Hittite"
                        }
                    ]
                ]
            }
        ]
    },
    {
        "number": "Rs. III 6",
        "transcription": [
            {
                "index": 15,
                "signs": [
                    [
                        {
                            "reading": "DINGIR",
                            "type": "Sumerogram"
                        },
                        {
                            "reading": "MEŠ",
                            "type": "Determination"
                        },
                        {
                            "reading": "LÚ",
                            "type": "Sumerogram"
                        },
                        {
                            "reading": "MEŠ",
                            "type": "Determination"
                        }
                    ],
                    [
                        {
                            "reading": "GIŠ",
                            "type": "Determination"
                        },
                        {
                            "reading": "ḫa",
                            "type": "Hittite"
                        },
                        {
                            "reading": "at",
                            "type": "Hittite"
                        },
                        {
                            "reading": "tal",
                            "type": "Hittite"
                        },
                        {
                            "reading": "wa",
                            "type": "Hittite"
                        },
                        {
                            "reading": "an",
                            "type": "Hittite"
                        },
                        {
                            "reading": "za",
                            "type": "Hittite"
                        }
                    ],
                    [
                        {
                            "reading": "GIM",
                            "type": "Sumerogram"
                        },
                        {
                            "reading": "an",
                            "type": "Hittite"
                        }
                    ]
                ]
            }
        ]
    },
    {
        "number": "Rs. III 7",
        "transcription": [
            {
                "index": 15,
                "signs": [
                    [
                        {
                            "reading": "GIŠ",
                            "type": "Determination"
                        },
                        {
                            "reading": "SAG",
                            "type": "Sumerogram"
                        },
                        {
                            "reading": "KUL",
                            "type": "Sumerogram"
                        }
                    ],
                    [
                        {
                            "reading": "EGIR",
                            "type": "Sumerogram"
                        },
                        {
                            "reading": "pa",
                            "type": "Hittite"
                        }
                    ],
                    [
                        {
                            "reading": "na",
                            "type": "Hittite"
                        },
                        {
                            "reading": "an",
                            "type": "Hittite"
                        },
                        {
                            "reading": "na",
                            "type": "Hittite"
                        },
                        {
                            "reading": "a",
                            "type": "Hittite"
                        },
                        {
                            "reading": "i",
                            "type": "Hittite"
                        }
                    ]
                ]
            }
        ]
    },
    {
        "number": "Rs. III 8",
        "transcription": [
            {
                "index": 16,
                "signs": [
                    [
                        {
                            "reading": "GIŠ",
                            "type": "Determination"
                        },
                        {
                            "reading": "IG",
                            "type": "Sumerogram"
                        },
                        {
                            "reading": "ya",
                            "type": "Hittite"
                        }
                    ],
                    [
                        {
                            "reading": "EGIR",
                            "type": "Sumerogram"
                        },
                        {
                            "reading": "pa",
                            "type": "Hittite"
                        }
                    ],
                    [
                        {
                            "reading": "ḫé",
                            "type": "Hittite"
                        },
                        {
                            "reading": "eš",
                            "type": "Hittite"
                        },
                        {
                            "reading": "ki",
                            "type": "Hittite"
                        },
                        {
                            "reading": "iz",
                            "type": "Hittite"
                        },
                        {
                            "reading": "zi",
                            "type": "Hittite"
                        }
                    ]
                ]
            }
        ]
    },
    {
        "number": "Rs. III 9",
        "transcription": [
            {
                "index": 17,
                "signs": [
                    [
                        {
                            "reading": "LUGAL",
                            "type": "Sumerogram"
                        },
                        {
                            "reading": "i",
                            "type": "Hittite"
                        },
                        {
                            "reading": "ia",
                            "type": "Hittite"
                        }
                    ],
                    [
                        {
                            "reading": "ḪUL",
                            "type": "Sumerogram"
                        },
                        {
                            "reading": "u",
                            "type": "Hittite"
                        },
                        {
                            "reading": "wa",
                            "type": "Hittite"
                        },
                        {
                            "reading": "aš",
                            "type": "Hittite"
                        }
                    ],
                    [
                        {
                            "reading": "UN",
                            "type": "Sumerogram"
                        },
                        {
                            "reading": "MEŠ",
                            "type": "Determination"
                        }
                    ],
                    [
                        {
                            "reading": "AN",
                            "type": "Akkadogram"
                        },
                        {
                            "reading": "ZE",
                            "type": "Akkadogram"
                        },
                        {
                            "reading": "EL",
                            "type": "Akkadogram"
                        },
                        {
                            "reading": "LU",
                            "type": "Akkadogram"
                        }
                    ]
                ]
            }
        ]
    },
    {
        "number": "Rs. III 10",
        "transcription": [
            {
                "index": 17,
                "signs": [
                    [
                        {
                            "reading": "ḫur",
                            "type": "Hittite"
                        },
                        {
                            "reading": "ki",
                            "type": "Hittite"
                        },
                        {
                            "reading": "il",
                            "type": "Hittite"
                        }
                    ],
                    [
                        {
                            "reading": "pa",
                            "type": "Hittite"
                        },
                        {
                            "reading": "ap",
                            "type": "Hittite"
                        },
                        {
                            "reading": "ra",
                            "type": "Hittite"
                        },
                        {
                            "reading": "tar",
                            "type": "Hittite"
                        }
                    ],
                    [
                        {
                            "reading": "mu",
                            "type": "Hittite"
                        },
                        {
                            "reading": "la",
                            "type": "Hittite"
                        },
                        {
                            "reading": "a",
                            "type": "Hittite"
                        },
                        {
                            "reading": "tar",
                            "type": "Hittite"
                        }
                    ]
                ]
            }
        ]
    },
    {
        "number": "Rs. III 11",
        "transcription": [
            {
                "index": 17,
                "signs": [
                    [
                        {
                            "reading": "QA",
                            "type": "Akkadogram"
                        },
                        {
                            "reading": "TAM",
                            "type": "Akkadogram"
                        },
                        {
                            "reading": "MA",
                            "type": "Akkadogram"
                        }
                    ],
                    [
                        {
                            "reading": "ar",
                            "type": "Hittite"
                        },
                        {
                            "reading": "ḫa",
                            "type": "Hittite"
                        }
                    ],
                    [
                        {
                            "reading": "a",
                            "type": "Hittite"
                        },
                        {
                            "reading": "ra",
                            "type": "Hittite"
                        },
                        {
                            "reading": "id",
                            "type": "Hittite"
                        },
                        {
                            "reading": "du",
                            "type": "Hittite"
                        }
                    ]
                ]
            }
        ]
    }
]